matherly.py
matherly-0.1.0.dist-info/METADATA
matherly-0.1.0.dist-info/WHEEL
matherly-0.1.0.dist-info/RECORD
