Metadata-Version: 2.1
Name: matherly
Version: 0.1.0
Summary: Math, math and more math.
Author: Nicolaj Figaw
Author-email: nope@example.com
Requires-Python: >=3.11.2,<4.0.0
Classifier: Programming Language :: Python :: 3
Requires-Dist: figonacci (>=0.1.1,<0.2.0)
